PyJoplin/__init__.py
PyJoplin/helpers/__init__.py
PyJoplin/helpers/http_helper.py
PyJoplin-0.0.1.dist-info/METADATA
PyJoplin-0.0.1.dist-info/WHEEL
PyJoplin-0.0.1.dist-info/top_level.txt
PyJoplin-0.0.1.dist-info/RECORD
